{
  "generated_at": "2026-04-18T23:59:52+09:00",
  "windows": {
    "7": {
      "totals": {
        "visits": 53,
        "users": 10,
        "pageviews": 141,
        "article_clicks": 53,
        "article_ctr": 0.375887,
        "avg_engagement_sec": 234.84
      },
      "prev": {
        "visits": 48,
        "users": 11,
        "pageviews": 106,
        "article_clicks": 52,
        "article_ctr": 0.490566,
        "avg_engagement_sec": 223.09
      },
      "range": {
        "from": "2026-04-12",
        "to": "2026-04-18"
      }
    },
    "30": {
      "totals": {
        "visits": 187,
        "users": 28,
        "pageviews": 644,
        "article_clicks": 189,
        "article_ctr": 0.293478,
        "avg_engagement_sec": 328.61
      },
      "prev": {
        "visits": 0,
        "users": 0,
        "pageviews": 0,
        "article_clicks": 0,
        "article_ctr": 0.0,
        "avg_engagement_sec": 0.0
      },
      "range": {
        "from": "2026-03-20",
        "to": "2026-04-18"
      }
    },
    "90": {
      "totals": {
        "visits": 187,
        "users": 28,
        "pageviews": 644,
        "article_clicks": 189,
        "article_ctr": 0.293478,
        "avg_engagement_sec": 328.61
      },
      "prev": {
        "visits": 0,
        "users": 0,
        "pageviews": 0,
        "article_clicks": 0,
        "article_ctr": 0.0,
        "avg_engagement_sec": 0.0
      },
      "range": {
        "from": "2026-01-19",
        "to": "2026-04-18"
      }
    }
  }
}
